llama_index/tools/jira_issue/__init__.py
llama_index/tools/jira_issue/base.py
llama_index_tools_jira_issue-0.2.1.dist-info/METADATA
llama_index_tools_jira_issue-0.2.1.dist-info/WHEEL
llama_index_tools_jira_issue-0.2.1.dist-info/licenses/LICENSE
llama_index_tools_jira_issue-0.2.1.dist-info/RECORD
