Metadata-Version: 2.4
Name: llama-index-tools-jira-issue
Version: 0.2.1
Author-email: Renyi Qu <mikustokes@gmail.com>
License-File: LICENSE
Requires-Python: <4.0,>=3.9
Requires-Dist: jira>=3.8.0
Requires-Dist: llama-index-core>=0.12.0
